README.txt
setup.py
dockend/__init__.py
dockend/dockend.py
dockend.egg-info/PKG-INFO
dockend.egg-info/SOURCES.txt
dockend.egg-info/dependency_links.txt
dockend.egg-info/entry_points.txt
dockend.egg-info/requires.txt
dockend.egg-info/top_level.txt