Metadata-Version: 1.1
Name: dockend
Version: 0.2.1
Summary: Change backend for BYR-Microservices and DLA-backend-services
Home-page: https://github.com/ChrisVidal10/dockend
Author: Christian Vidal
Author-email: chris.vidal10@gmail.com
License: UNKNOWN
Keywords: sample setuptools development docker
Platform: UNKNOWN
Classifier: Development Status :: 4 - Beta
Classifier: Intended Audience :: Developers
Classifier: License :: OSI Approved :: MIT License
Classifier: Programming Language :: Python :: 3.6
